bitorchinfo/__init__.py
bitorchinfo/formatting.py
bitorchinfo/layer_info.py
bitorchinfo/model_statistics.py
bitorchinfo/torchinfo.py
bitorchinfo-0.1.0.dist-info/LICENSE
bitorchinfo-0.1.0.dist-info/METADATA
bitorchinfo-0.1.0.dist-info/WHEEL
bitorchinfo-0.1.0.dist-info/top_level.txt
bitorchinfo-0.1.0.dist-info/RECORD
