Metadata-Version: 2.1
Name: bitorchinfo
Version: 0.1.0
Summary: Model summary for bitorch, based on the original torchinfo.
Home-page: https://github.com/hpi-xnor/bittorchinfo
Author: Joseph Bethge
Author-email: joseph.bethge@hpi.de
License: MIT
Keywords: bitorch bitorchinfo torch pytorch torchsummary torch-summary summary keras deep-learning ml torchinfo torch-info visualize model statistics layer stats
Platform: UNKNOWN
Classifier: License :: OSI Approved :: MIT License
Classifier: Operating System :: OS Independent
Classifier: Programming Language :: Python :: 3
Classifier: Programming Language :: Python :: 3 :: Only
Classifier: Programming Language :: Python :: 3.6
Classifier: Programming Language :: Python :: 3.7
Classifier: Programming Language :: Python :: 3.8
Classifier: Programming Language :: Python :: 3.9
Classifier: Programming Language :: Python :: 3.10
Requires-Python: >=3.6
License-File: LICENSE
